pybound/__init__.py
pybound-1.0.5.dist-info/WHEEL
pybound-1.0.5.dist-info/METADATA
pybound-1.0.5.dist-info/RECORD
