Metadata-Version: 2.1
Name: pybound
Version: 1.0.5
Summary: pyBound is a collection of helpful functions that are useful in almost every python file.
Home-page: https://pypi.org/project/pybound/
Author: Xhaiden D'Souza
Author-email: xhaidendsouza@gmail.com
Requires-Python: >=3.8,<4.0
Classifier: Programming Language :: Python :: 3
Classifier: Programming Language :: Python :: 3.10
Classifier: Programming Language :: Python :: 3.8
Classifier: Programming Language :: Python :: 3.9
Project-URL: Documentation, https://pypi.org/project/pybound/#description
